<?xml version='1.0' encoding='UTF-8'?><soapenv:Envelope xmlns:soapenv="http://schemas.xmlsoap.org/soap/envelope/"><soapenv:Body><ns6:executeCommandByParamListResponse xmlns:ns6="http://bladelogic.com/webservices/skeleton/clitunnel"><ns6:return><ns3:classInstance xmlns:ns3="http://bladelogic.com/webservices/model/clitunnel/xsd">false</ns3:classInstance><ns3:comments xmlns:ns3="http://bladelogic.com/webservices/model/clitunnel/xsd">No comments</ns3:comments><ns3:executionTime xmlns:ns3="http://bladelogic.com/webservices/model/clitunnel/xsd">0</ns3:executionTime><ns3:list xmlns:ns3="http://bladelogic.com/webservices/model/clitunnel/xsd">false</ns3:list><ns3:memoryUsed xmlns:ns3="http://bladelogic.com/webservices/model/clitunnel/xsd">0</ns3:memoryUsed><ns3:realInputArguments xmlns:ns3="http://bladelogic.com/webservices/model/clitunnel/xsd" xmlns:s5="http://www.w3.org/2001/XMLSchema-instance" xmlns:s6="http://www.w3.org/2001/XMLSchema" s5:type="s6:string">31</ns3:realInputArguments><ns3:returnValue xmlns:ns3="http://bladelogic.com/webservices/model/clitunnel/xsd" xmlns:s7="http://www.w3.org/2001/XMLSchema-instance" xmlns:s8="http://www.w3.org/2001/XMLSchema" s7:type="s8:string">&lt;?xml version="1.0" encoding="UTF-8" standalone="yes"?>&lt;VirtualGuestPackageConfiguration>    &lt;GeneralInfo>        &lt;PackageName>VMW-W2k8-64B-20GB&lt;/PackageName>        &lt;PackageDescription>VMW-W2k8-64B-20GB&lt;/PackageDescription>        &lt;DepotGroupId>2000015&lt;/DepotGroupId>        &lt;VirtualGuestPackageType>2&lt;/VirtualGuestPackageType>        &lt;VirtualGuestName>test&lt;/VirtualGuestName>    &lt;/GeneralInfo>    &lt;PlatformInfo>        &lt;VMwareInfo>            &lt;ClonedDiskFormat>sameAsSource&lt;/ClonedDiskFormat>            &lt;IsCustomConfig>false&lt;/IsCustomConfig>            &lt;VMXDatastore>Templates-vmfs-Aus-HDSG1K-01-40:4A&lt;/VMXDatastore>            &lt;VMXDatastoreType>Datastore&lt;/VMXDatastoreType>            &lt;VMFolderPath>/Temp VMs&lt;/VMFolderPath>            &lt;GuestOSId>1&lt;/GuestOSId>            &lt;GuestOSVersionId>26&lt;/GuestOSVersionId>            &lt;PowerOnVMAfterCreation>true&lt;/PowerOnVMAfterCreation>            &lt;NumOfProcessors>2&lt;/NumOfProcessors>            &lt;MemoryInMB>4096&lt;/MemoryInMB>            &lt;VMwareDiskSettings>                &lt;DiskInfo>                    &lt;DiskSize>20480&lt;/DiskSize>                    &lt;DiskSizeUnit>MB&lt;/DiskSizeUnit>                    &lt;Datastore>Templates-vmfs-Aus-HDSG1K-01-40:4A&lt;/Datastore>                    &lt;DatastoreType>Datastore&lt;/DatastoreType>                    &lt;ThinProvisioning>true&lt;/ThinProvisioning>                &lt;/DiskInfo>            &lt;/VMwareDiskSettings>            &lt;VMwareNetworkSettings>                &lt;NetworkConnection>                    &lt;Network>Management-202&lt;/Network>                    &lt;Adapter>E1000&lt;/Adapter>                    &lt;ConnectAtPowerOn>true&lt;/ConnectAtPowerOn>                &lt;/NetworkConnection>            &lt;/VMwareNetworkSettings>            &lt;OSCustomizationInfo>                &lt;WindowsCustomizationInfo>                    &lt;ComputerName>test&lt;/ComputerName>                    &lt;AdminPassword>BLencrypt:OAUAPOQTEQBNKLQLMQBNZQOEEMPOPTPXTTKMPAXUMNAMWBLWZPTVAMLPBQBLZKNN&lt;/AdminPassword>                    &lt;Workgroup>WORKGROUP&lt;/Workgroup>                    &lt;UserName>bmc&lt;/UserName>                    &lt;Organization>bmc&lt;/Organization>                    &lt;LicenseKey>&lt;/LicenseKey>                    &lt;LicenseType>perServer&lt;/LicenseType>                    &lt;NumOfConnections>5&lt;/NumOfConnections>                    &lt;TimezoneId>1&lt;/TimezoneId>                    &lt;LocaleId>1&lt;/LocaleId>                &lt;/WindowsCustomizationInfo>            &lt;/OSCustomizationInfo>        &lt;/VMwareInfo>    &lt;/PlatformInfo>&lt;/VirtualGuestPackageConfiguration></ns3:returnValue><ns3:success xmlns:ns3="http://bladelogic.com/webservices/model/clitunnel/xsd">true</ns3:success></ns6:return></ns6:executeCommandByParamListResponse></soapenv:Body></soapenv:Envelope>